dhasher/__init__.py
dhasher/myhash.py
dhasher-0.1.1.dist-info/METADATA
dhasher-0.1.1.dist-info/WHEEL
dhasher-0.1.1.dist-info/top_level.txt
dhasher-0.1.1.dist-info/RECORD
