Metadata-Version: 2.1
Name: dhasher
Version: 0.1.1
Summary: A python library for password hashing and verification existing password hashes
Home-page: UNKNOWN
Author: Geoffrey Israel
Author-email: israelgeoffrey13@gmail.com
License: MIT
Platform: UNKNOWN
